server.py
8000_cherry_mcp-0.1.0.dist-info/METADATA
8000_cherry_mcp-0.1.0.dist-info/WHEEL
8000_cherry_mcp-0.1.0.dist-info/top_level.txt
8000_cherry_mcp-0.1.0.dist-info/RECORD
